aspose/__init__.py
aspose/pycore.cp310-win_amd64.pyd
aspose/pycore.cp311-win_amd64.pyd
aspose/pycore.cp312-win_amd64.pyd
aspose/pycore.cp313-win_amd64.pyd
aspose/pycore.cp36-win_amd64.pyd
aspose/pycore.cp37-win_amd64.pyd
aspose/pycore.cp38-win_amd64.pyd
aspose/pycore.cp39-win_amd64.pyd
aspose/pydrawing.cp310-win_amd64.pyd
aspose/pydrawing.cp311-win_amd64.pyd
aspose/pydrawing.cp312-win_amd64.pyd
aspose/pydrawing.cp313-win_amd64.pyd
aspose/pydrawing.cp36-win_amd64.pyd
aspose/pydrawing.cp37-win_amd64.pyd
aspose/pydrawing.cp38-win_amd64.pyd
aspose/pydrawing.cp39-win_amd64.pyd
aspose/pygc.cp310-win_amd64.pyd
aspose/pygc.cp311-win_amd64.pyd
aspose/pygc.cp312-win_amd64.pyd
aspose/pygc.cp313-win_amd64.pyd
aspose/pygc.cp36-win_amd64.pyd
aspose/pygc.cp37-win_amd64.pyd
aspose/pygc.cp38-win_amd64.pyd
aspose/pygc.cp39-win_amd64.pyd
aspose/pyreflection.cp310-win_amd64.pyd
aspose/pyreflection.cp311-win_amd64.pyd
aspose/pyreflection.cp312-win_amd64.pyd
aspose/pyreflection.cp313-win_amd64.pyd
aspose/pyreflection.cp36-win_amd64.pyd
aspose/pyreflection.cp37-win_amd64.pyd
aspose/pyreflection.cp38-win_amd64.pyd
aspose/pyreflection.cp39-win_amd64.pyd
aspose/words.cp310-win_amd64.pyd
aspose/words.cp311-win_amd64.pyd
aspose/words.cp312-win_amd64.pyd
aspose/words.cp313-win_amd64.pyd
aspose/words.cp36-win_amd64.pyd
aspose/words.cp37-win_amd64.pyd
aspose/words.cp38-win_amd64.pyd
aspose/words.cp39-win_amd64.pyd
aspose/__pyinstaller/__init__.pyi
aspose/__pyinstaller/hook-aspose.py
aspose/assemblies/pycore/WrpInterop.Aspose.PyCore.dll
aspose/assemblies/pydrawing/Microsoft.Win32.SystemEvents.dll
aspose/assemblies/pydrawing/System.Drawing.Common.dll
aspose/assemblies/pydrawing/WrpInterop.Aspose.PyDrawing.dll
aspose/assemblies/pygc/Aspose.PyGC.dll
aspose/assemblies/pyreflection/WrpInterop.Aspose.PyReflection.dll
aspose/assemblies/words/Aspose.Words.dll
aspose/assemblies/words/Autofac.dll
aspose_words-26.1.0.dist-info/METADATA
aspose_words-26.1.0.dist-info/WHEEL
aspose_words-26.1.0.dist-info/entry_points.txt
aspose_words-26.1.0.dist-info/top_level.txt
aspose_words-26.1.0.dist-info/RECORD
