Metadata-Version: 2.1
Name: aspose-words
Version: 26.1.0
Summary: Aspose.Words for Python is a Document Processing library that allows developers to work with documents in many popular formats without needing Office Automation.
Home-page: https://products.aspose.com/words/python-net/
Author: Aspose
Project-URL: Docs, https://docs.aspose.com/words/python-net/
Project-URL: Release Notes, https://releases.aspose.com/words/python/release-notes/2026/aspose-words-for-python-via-dotnet-26-1-release-notes/
Project-URL: Demos, https://products.aspose.app/words/family
Project-URL: API Reference, https://reference.aspose.com/words/python-net/
Project-URL: Examples, https://github.com/aspose-words/Aspose.Words-for-Python-via-.NET/
Project-URL: Blog, https://blog.aspose.com/category/words/
Project-URL: Free Support, https://forum.aspose.com/c/words
Project-URL: Temporary License, https://purchase.aspose.com/temporary-license
Keywords: doc,docx to pdf,convert,compare,create,edit,word,split,bmp,rtf,odt,open office,html,tiff,dot,wordml,mobi,chm,txt,md,markdown,xps,svg,ps,postscript,pcl,epub,png,emf,jpg,gif,mail merge,table,reporting,document
Platform: win_amd64
Classifier: Development Status :: 5 - Production/Stable
Classifier: Intended Audience :: Developers
Classifier: Intended Audience :: Education
Classifier: License :: Other/Proprietary License
Classifier: License :: Free To Use But Restricted
Classifier: Operating System :: Microsoft :: Windows
Classifier: Operating System :: Unix
Classifier: Operating System :: POSIX
Classifier: Operating System :: MacOS :: MacOS X
Classifier: Programming Language :: Python :: 3
Classifier: Programming Language :: Python :: 3 :: Only
Classifier: Programming Language :: Python :: 3.6
Classifier: Programming Language :: Python :: 3.7
Classifier: Programming Language :: Python :: 3.8
Classifier: Programming Language :: Python :: 3.9
Classifier: Programming Language :: Python :: 3.10
Classifier: Programming Language :: Python :: 3.11
Classifier: Programming Language :: Python :: 3.12
Classifier: Programming Language :: Python :: 3.13
Classifier: Topic :: Software Development
Classifier: Topic :: Software Development :: Libraries
Classifier: Topic :: Office/Business
Classifier: Topic :: Office/Business :: Office Suites
Classifier: Topic :: Text Processing
Classifier: Topic :: Text Processing :: Markup
Requires-Python: >=3.6,<3.14
